src/__init__.py
src/core/__init__.py
src/core/audio/__init__.py
src/core/audio/audio_clip.py
src/core/audio/audio_manager.py
src/core/ecs/__init__.py
src/core/ecs/component.py
src/core/ecs/components/__init__.py
src/core/ecs/components/sprite_renderer.py
src/core/ecs/components/transform.py
src/core/ecs/entity.py
src/core/ecs/world.py
src/core/game_loop.py
src/core/input.py
src/core/physics.py
src/core/scene.py
src/core/scene_manager.py
src/core/sprite.py
src/core/sprite_renderer.py
src/core/tilemap.py
src/core/ui/__init__.py
src/core/ui/button.py
src/core/ui/text.py
src/core/ui/ui_element.py
src/core/vector2d.py
src/core/window.py
retro_game_engine-0.2.2.dist-info/LICENSE
retro_game_engine-0.2.2.dist-info/METADATA
retro_game_engine-0.2.2.dist-info/WHEEL
retro_game_engine-0.2.2.dist-info/entry_points.txt
retro_game_engine-0.2.2.dist-info/RECORD
