Metadata-Version: 2.1
Name: retro-game-engine
Version: 0.2.2
Summary: A retro-style game engine built with Pygame
Home-page: https://github.com/ahmed5145/retro_game_engine
License: MIT
Keywords: game,engine,pygame,retro,2d
Author: Ahmed Mohamed
Author-email: ahmedmohmaed200354@gmail.com
Requires-Python: >=3.9,<4.0
Classifier: Development Status :: 4 - Beta
Classifier: Intended Audience :: Developers
Classifier: License :: OSI Approved :: MIT License
Classifier: Programming Language :: Python :: 3
Classifier: Programming Language :: Python :: 3.9
Classifier: Programming Language :: Python :: 3.10
Classifier: Programming Language :: Python :: 3.11
Classifier: Programming Language :: Python :: 3.12
Classifier: Topic :: Games/Entertainment
Classifier: Topic :: Software Development :: Libraries :: pygame
Requires-Dist: numpy (==1.26.3)
Requires-Dist: pillow (>=10.0.0,<11.0.0)
Requires-Dist: pygame (>=2.5.2,<3.0.0)
Project-URL: Bug Tracker, https://github.com/ahmed5145/retro_game_engine/issues
Project-URL: Documentation, https://retro-game-engine.readthedocs.io
Project-URL: Repository, https://github.com/ahmed5145/retro_game_engine
Project-URL: Source Code, https://github.com/ahmed5145/retro_game_engine
